{
    "name": "Barnes, Brantley",
    "scoring_average": 92.0,
    "rounds": [
        {
            "date": "2020-02-24",
            "date_timestamp": 737479,
            "score": 92,
            "total": 92,
            "name": "Round 11 (Wed, February 24)",
            "valid": false,
            "reason": "Round date 2021-02-24, does not fall within season (2021-04-01 to 2021-10-01)",
            "front": [
                {
                    "score": 7,
                    "type": "plus2"
                },
                {
                    "score": 5,
                    "type": "plus1"
                },
                {
                    "score": 4,
                    "type": "plus1"
                },
                {
                    "score": 4,
                    "type": "par"
                },
                {
                    "score": 8,
                    "type": "plus2"
                },
                {
                    "score": 5,
                    "type": "plus1"
                },
                {
                    "score": 8,
                    "type": "plus2"
                },
                {
                    "score": 4,
                    "type": "plus1"
                },
                {
                    "score": 6,
                    "type": "plus2"
                }
            ],
            "back": [
                {
                    "score": 6,
                    "type": "plus1"
                },
                {
                    "score": 3,
                    "type": "par"
                },
                {
                    "score": 5,
                    "type": "plus1"
                },
                {
                    "score": 4,
                    "type": "par"
                },
                {
                    "score": 5,
                    "type": "par"
                },
                {
                    "score": 3,
                    "type": "par"
                },
                {
                    "score": 4,
                    "type": "par"
                },
                {
                    "score": 5,
                    "type": "plus1"
                },
                {
                    "score": 6,
                    "type": "plus2"
                }
            ],
            "in": 41,
            "out": 51
        }
    ]
}