{
    "name": "Rogers, Ken",
    "scoring_average": 78.667,
    "rounds": [
        {
            "date": "2022-02-25",
            "date_timestamp": 738211,
            "score": 78,
            "total": 78,
            "name": "Round 13 (Fri, February 25)",
            "valid": true,
            "reason": null,
            "front": [
                {
                    "score": 7,
                    "type": "plus2"
                },
                {
                    "score": 4,
                    "type": "par"
                },
                {
                    "score": 3,
                    "type": "par"
                },
                {
                    "score": 5,
                    "type": "plus1"
                },
                {
                    "score": 4,
                    "type": "birdie"
                },
                {
                    "score": 4,
                    "type": "par"
                },
                {
                    "score": 4,
                    "type": "par"
                },
                {
                    "score": 3,
                    "type": "par"
                },
                {
                    "score": 4,
                    "type": "par"
                }
            ],
            "back": [
                {
                    "score": 6,
                    "type": "plus1"
                },
                {
                    "score": 3,
                    "type": "par"
                },
                {
                    "score": 4,
                    "type": "par"
                },
                {
                    "score": 6,
                    "type": "plus2"
                },
                {
                    "score": 4,
                    "type": "birdie"
                },
                {
                    "score": 3,
                    "type": "par"
                },
                {
                    "score": 4,
                    "type": "par"
                },
                {
                    "score": 5,
                    "type": "plus1"
                },
                {
                    "score": 5,
                    "type": "plus1"
                }
            ],
            "in": 40,
            "out": 38
        },
        {
            "date": "2022-03-18",
            "date_timestamp": 738232,
            "score": 78,
            "total": 78,
            "name": "Round 17 (Fri, March 18)",
            "valid": true,
            "reason": null,
            "front": [
                {
                    "score": 5,
                    "type": "par"
                },
                {
                    "score": 4,
                    "type": "par"
                },
                {
                    "score": 3,
                    "type": "par"
                },
                {
                    "score": 4,
                    "type": "par"
                },
                {
                    "score": 7,
                    "type": "plus2"
                },
                {
                    "score": 5,
                    "type": "plus1"
                },
                {
                    "score": 5,
                    "type": "plus1"
                },
                {
                    "score": 4,
                    "type": "plus1"
                },
                {
                    "score": 3,
                    "type": "birdie"
                }
            ],
            "back": [
                {
                    "score": 6,
                    "type": "plus1"
                },
                {
                    "score": 3,
                    "type": "par"
                },
                {
                    "score": 3,
                    "type": "birdie"
                },
                {
                    "score": 4,
                    "type": "par"
                },
                {
                    "score": 6,
                    "type": "plus1"
                },
                {
                    "score": 3,
                    "type": "par"
                },
                {
                    "score": 5,
                    "type": "plus1"
                },
                {
                    "score": 3,
                    "type": "birdie"
                },
                {
                    "score": 5,
                    "type": "plus1"
                }
            ],
            "in": 38,
            "out": 40
        },
        {
            "date": "2022-03-25",
            "date_timestamp": 738239,
            "score": 80,
            "total": 80,
            "name": "March 25 (Fri, March 25)",
            "valid": true,
            "reason": null,
            "front": [
                {
                    "score": 6,
                    "type": "plus1"
                },
                {
                    "score": 3,
                    "type": "birdie"
                },
                {
                    "score": 5,
                    "type": "plus2"
                },
                {
                    "score": 4,
                    "type": "par"
                },
                {
                    "score": 6,
                    "type": "plus1"
                },
                {
                    "score": 5,
                    "type": "plus1"
                },
                {
                    "score": 3,
                    "type": "birdie"
                },
                {
                    "score": 5,
                    "type": "plus2"
                },
                {
                    "score": 4,
                    "type": "par"
                }
            ],
            "back": [
                {
                    "score": 6,
                    "type": "plus1"
                },
                {
                    "score": 3,
                    "type": "par"
                },
                {
                    "score": 5,
                    "type": "plus1"
                },
                {
                    "score": 5,
                    "type": "plus1"
                },
                {
                    "score": 4,
                    "type": "birdie"
                },
                {
                    "score": 4,
                    "type": "plus1"
                },
                {
                    "score": 5,
                    "type": "plus1"
                },
                {
                    "score": 4,
                    "type": "par"
                },
                {
                    "score": 3,
                    "type": "birdie"
                }
            ],
            "in": 39,
            "out": 41
        }
    ]
}