{
    "name": "Smith, Phil",
    "scoring_average": 75.5,
    "rounds": [
        {
            "date": "2022-05-29",
            "date_timestamp": 738304,
            "score": 76,
            "total": 76,
            "name": "Round 43 (Mon, May 29)",
            "valid": false,
            "reason": "Not all players finished 18 holes",
            "front": [
                {
                    "score": 5,
                    "type": "par"
                },
                {
                    "score": 5,
                    "type": "plus1"
                },
                {
                    "score": 3,
                    "type": "par"
                },
                {
                    "score": 3,
                    "type": "birdie"
                },
                {
                    "score": 5,
                    "type": "par"
                },
                {
                    "score": 5,
                    "type": "plus1"
                },
                {
                    "score": 4,
                    "type": "par"
                },
                {
                    "score": 3,
                    "type": "par"
                },
                {
                    "score": 4,
                    "type": "par"
                }
            ],
            "back": [
                {
                    "score": 5,
                    "type": "par"
                },
                {
                    "score": 3,
                    "type": "par"
                },
                {
                    "score": 4,
                    "type": "par"
                },
                {
                    "score": 4,
                    "type": "par"
                },
                {
                    "score": 6,
                    "type": "plus1"
                },
                {
                    "score": 4,
                    "type": "plus1"
                },
                {
                    "score": 4,
                    "type": "par"
                },
                {
                    "score": 5,
                    "type": "plus1"
                },
                {
                    "score": 4,
                    "type": "par"
                }
            ],
            "in": 39,
            "out": 37
        },
        {
            "date": "2022-07-07",
            "date_timestamp": 738343,
            "score": 75,
            "total": 75,
            "name": "Round 56 (Fri, July  7)",
            "valid": true,
            "reason": null,
            "front": [
                {
                    "score": 5,
                    "type": "par"
                },
                {
                    "score": 4,
                    "type": "par"
                },
                {
                    "score": 3,
                    "type": "par"
                },
                {
                    "score": 4,
                    "type": "par"
                },
                {
                    "score": 4,
                    "type": "birdie"
                },
                {
                    "score": 5,
                    "type": "plus1"
                },
                {
                    "score": 4,
                    "type": "par"
                },
                {
                    "score": 4,
                    "type": "plus1"
                },
                {
                    "score": 6,
                    "type": "plus2"
                }
            ],
            "back": [
                {
                    "score": 5,
                    "type": "par"
                },
                {
                    "score": 3,
                    "type": "par"
                },
                {
                    "score": 5,
                    "type": "plus1"
                },
                {
                    "score": 4,
                    "type": "par"
                },
                {
                    "score": 5,
                    "type": "par"
                },
                {
                    "score": 2,
                    "type": "birdie"
                },
                {
                    "score": 4,
                    "type": "par"
                },
                {
                    "score": 4,
                    "type": "par"
                },
                {
                    "score": 4,
                    "type": "par"
                }
            ],
            "in": 36,
            "out": 39
        }
    ]
}